autodecrypt/__init__.py
autodecrypt/decrypt_img.py
autodecrypt/fw_utils.py
autodecrypt/ipsw_dl.py
autodecrypt/ipsw_utils.py
autodecrypt/main.py
autodecrypt/pongo.py
autodecrypt/scrapkeys.py
autodecrypt/utils.py
autodecrypt-2.3.2.dist-info/entry_points.txt
autodecrypt-2.3.2.dist-info/LICENSE
autodecrypt-2.3.2.dist-info/WHEEL
autodecrypt-2.3.2.dist-info/METADATA
autodecrypt-2.3.2.dist-info/RECORD
