Metadata-Version: 2.1
Name: autodecrypt
Version: 2.3.2
Summary: Tool to decrypt iOS firmware images
Home-page: https://github.com/matteyeux/autodecrypt
License: MIT
Keywords: autodecrypt,iOS,iBoot,checkm8
Author: matteyeux
Requires-Python: >=3.7,<4.0
Classifier: Development Status :: 5 - Production/Stable
Classifier: Intended Audience :: Developers
Classifier: Intended Audience :: Information Technology
Classifier: License :: OSI Approved :: MIT License
Classifier: Programming Language :: Python :: 3
Classifier: Programming Language :: Python :: 3.10
Classifier: Programming Language :: Python :: 3.7
Classifier: Programming Language :: Python :: 3.8
Classifier: Programming Language :: Python :: 3.9
Classifier: Topic :: Utilities
Requires-Dist: beautifulsoup4 (>=4.9.3,<5.0.0)
Requires-Dist: pyimg4 (>=0.6.2,<0.7.0)
Requires-Dist: pyquery (>=1.4.1,<2.0.0)
Requires-Dist: pyusb (>=1.0.2,<2.0.0)
Requires-Dist: remotezip (>=0.9.2,<0.10.0)
Requires-Dist: rich (>=12.4.4,<13.0.0)
Requires-Dist: typer (>=0.4.1,<0.5.0)
Project-URL: Repository, https://github.com/matteyeux/autodecrypt
